<?xml version="1.0" encoding="UTF-8"?>
<con:soapui-project id="8193766e-f842-4cb7-b581-0cf2ea1f2a79" activeEnvironment="Default" name="REST Project 1" resourceRoot="" soapui-version="5.2.1" abortOnError="false" runType="SEQUENTIAL" xmlns:con="http://eviware.com/soapui/config"><con:settings/><con:interface xsi:type="con:RestService" id="6cdb5fd4-2af0-4f80-8073-94b73580d7dc" wadlVersion="http://wadl.dev.java.net/2009/02" name="https://mydev.ginstr.com" type="rest" xmlns:xsi="http://www.w3.org/2001/XMLSchema-instance"><con:settings/><con:definitionCache type="TEXT" rootPart=""/><con:endpoints><con:endpoint>https://mydev.ginstr.com</con:endpoint></con:endpoints><con:resource name="Table" path="/api/ag/db/table" id="754974e3-d5d1-442f-985f-1ae9a40f6136"><con:settings/><con:parameters><con:parameter><con:name>Authorization</con:name><con:value/><con:style>HEADER</con:style><con:default/><con:description xsi:nil="true"/></con:parameter></con:parameters><con:resource name="$(id)" path="{tableid}" id="d5a7fd3d-922a-40cb-bbd1-104fb78bf2ff"><con:settings/><con:parameters><con:parameter><con:name>tableid</con:name><con:value>tableid</con:value><con:style>TEMPLATE</con:style><con:default>tableid</con:default></con:parameter></con:parameters><con:method name="Method 1" id="580eff37-923c-4119-a619-770a01f4df6a" method="DELETE"><con:settings/><con:parameters/><con:representation type="REQUEST"><con:mediaType>application/json</con:mediaType><con:params/></con:representation><con:representation type="FAULT"><con:mediaType>application/json</con:mediaType><con:status>401</con:status><con:params/><con:element xmlns:tab="https://mydev.ginstr.com/api/ag/db/table/">tab:Fault</con:element></con:representation><con:representation type="FAULT"><con:mediaType>application/json;charset=UTF-8</con:mediaType><con:status>404</con:status><con:params/><con:element xmlns:tab="https://mydev.ginstr.com/api/ag/db/table">tab:Fault</con:element></con:representation><con:request name="Request 1" id="a08acdf9-c509-4e50-ac98-389f772d0695" mediaType="application/json" postQueryString="false"><con:settings><con:setting id="com.eviware.soapui.impl.wsdl.WsdlRequest@request-headers">&lt;xml-fragment/></con:setting></con:settings><con:endpoint>https://mydev.ginstr.com</con:endpoint><con:request/><con:originalUri>https://mydev.ginstr.com/api/ag/db/table/</con:originalUri><con:credentials><con:authType>No Authorization</con:authType></con:credentials><con:jmsConfig JMSDeliveryMode="PERSISTENT"/><con:jmsPropertyConfig/><con:parameters><entry key="tableid" value="" xmlns="http://eviware.com/soapui/config"/></con:parameters></con:request></con:method></con:resource><con:method name="Table" id="f278b970-afff-4775-89ea-091ff2b2efaf" method="POST"><con:settings/><con:parameters/><con:representation type="REQUEST"><con:mediaType>application/json</con:mediaType><con:params/></con:representation><con:representation type="FAULT"><con:mediaType>application/json</con:mediaType><con:status>401</con:status><con:params/><con:element xmlns:tab="https://mydev.ginstr.com/api/ag/db/table">tab:Fault</con:element></con:representation><con:representation type="FAULT"><con:mediaType>application/json;charset=UTF-8</con:mediaType><con:status>500 400</con:status><con:params/><con:element xmlns:tab="https://mydev.ginstr.com/api/ag/db/table">tab:Fault</con:element></con:representation><con:representation type="RESPONSE"><con:mediaType>application/json;charset=UTF-8</con:mediaType><con:status>200</con:status><con:params/><con:element xmlns:tab="https://mydev.ginstr.com/api/ag/db/table">tab:Response</con:element></con:representation><con:request name="Request 1" id="1ed9098e-1b3f-4f66-8a7c-f9962e43116c" mediaType="application/json" postQueryString="false"><con:settings><con:setting id="com.eviware.soapui.impl.wsdl.WsdlRequest@request-headers">&lt;xml-fragment/></con:setting></con:settings><con:endpoint>https://mydev.ginstr.com</con:endpoint><con:request>{"columns":[{"dataTypeDefinitionId":"text","id":"2eefe4c6f0bd406787d21fbb88a1a2f8","settings":{"len":null,"horizontalAlignment":"left","valuesList":[]},"name":"iti"}],"name":"alex","isTableEmpty":true}</con:request><con:originalUri>https://mydev.ginstr.com/api/ag/db/table</con:originalUri><con:credentials><con:authType>No Authorization</con:authType></con:credentials><con:jmsConfig JMSDeliveryMode="PERSISTENT"/><con:jmsPropertyConfig/><con:parameters><entry key="autorization" value="1f092f9f11f76bd0370b01ba33cd98a00b04ba44abd9ad0cac5056aa89a5234b" xmlns="http://eviware.com/soapui/config"/></con:parameters><con:parameterOrder><con:entry>Authorization</con:entry></con:parameterOrder></con:request></con:method><con:method name="GETtables" id="6ee7dbda-0a4a-45bb-adf2-d0bbfa83ec20" method="GET"><con:settings/><con:parameters/><con:representation type="RESPONSE"><con:mediaType>application/json;charset=UTF-8</con:mediaType><con:status>200</con:status><con:params/><con:element>Response</con:element></con:representation><con:representation type="FAULT"><con:mediaType>application/json</con:mediaType><con:status>401</con:status><con:params/><con:element xmlns:tab="https://mydev.ginstr.com/api/ag/db/table">tab:Fault</con:element></con:representation><con:request name="Request 1" id="edf50cf2-425c-428f-b79c-76fd038568d9" mediaType="application/json"><con:settings><con:setting id="com.eviware.soapui.impl.wsdl.WsdlRequest@request-headers">&lt;xml-fragment/></con:setting></con:settings><con:endpoint>https://mydev.ginstr.com</con:endpoint><con:request/><con:originalUri>https://mydev.ginstr.com/api/ag/db/table</con:originalUri><con:credentials><con:authType>No Authorization</con:authType></con:credentials><con:jmsConfig JMSDeliveryMode="PERSISTENT"/><con:jmsPropertyConfig/><con:parameters><entry key="Authorization" value="8c8635562a7b7df3a747fa447d9c2b7cbdebe2e3facdfc854e50b2815ab53400" xmlns="http://eviware.com/soapui/config"/></con:parameters></con:request></con:method></con:resource></con:interface><con:interface xsi:type="con:RestService" id="91108c4f-a68f-4003-987b-f0a8ee9fe698" wadlVersion="http://wadl.dev.java.net/2009/02" name="https://158.181.53.211" type="rest" xmlns:xsi="http://www.w3.org/2001/XMLSchema-instance"><con:settings/><con:definitionCache type="TEXT" rootPart=""/><con:endpoints><con:endpoint>https://158.181.53.211</con:endpoint></con:endpoints><con:resource name="Login.json" path="/login.json" id="4e2fff6e-523e-4f21-a5d4-512741eba91c"><con:settings/><con:parameters/><con:method name="Login.json" id="18ff7217-103c-4656-8385-502b14ebbe4d" method="POST"><con:settings/><con:parameters/><con:representation type="FAULT"><con:mediaType>text/html;charset=utf-8</con:mediaType><con:status>400</con:status><con:params/><con:element>html</con:element></con:representation><con:representation type="REQUEST"><con:mediaType>application/json</con:mediaType><con:params/></con:representation><con:representation type="RESPONSE"><con:mediaType>application/json;charset=UTF-8</con:mediaType><con:status>200</con:status><con:params/><con:element xmlns:log="https://158.181.53.211/login.json">log:Response</con:element></con:representation><con:request name="Request 1" id="e1142e61-fb61-44c0-b83b-603616f7e725" mediaType="application/json" postQueryString="false"><con:settings><con:setting id="com.eviware.soapui.impl.wsdl.WsdlRequest@request-headers">&lt;xml-fragment/></con:setting></con:settings><con:endpoint>https://158.181.53.211</con:endpoint><con:request>{"username":"eizotov@hillel.com","password":"asdffdsA1"}</con:request><con:originalUri>https://158.181.53.211/login.json</con:originalUri><con:credentials><con:authType>No Authorization</con:authType></con:credentials><con:jmsConfig JMSDeliveryMode="PERSISTENT"/><con:jmsPropertyConfig/><con:parameters/></con:request></con:method></con:resource></con:interface><con:testSuite id="8642e745-05c6-454a-a50f-793246985a7f" name="TestSuite 1"><con:settings/><con:runType>SEQUENTIAL</con:runType><con:testCase id="a981fe9a-95ed-4954-80f7-ee1f19c82928" failOnError="true" failTestCaseOnErrors="true" keepSession="false" maxResults="0" name="CreateTableSimple" searchProperties="true"><con:settings/><con:testStep type="properties" name="TestData" id="32723e4d-bdb1-4cf6-8d4c-15ab4ed2123e"><con:settings/><con:config xsi:type="con:PropertiesStep" saveFirst="true" xmlns:xsi="http://www.w3.org/2001/XMLSchema-instance"><con:properties><con:property><con:name>tableName</con:name><con:value>reverance123</con:value></con:property><con:property><con:name>username</con:name><con:value>eizotov@hillel.com</con:value></con:property><con:property><con:name>password</con:name><con:value>asdffdsA1</con:value></con:property></con:properties></con:config></con:testStep><con:testStep type="properties" name="TEMP" id="4dabb1a3-ad28-403c-b721-ed2a3d5e21e7"><con:settings/><con:config xsi:type="con:PropertiesStep" saveFirst="true" xmlns:xsi="http://www.w3.org/2001/XMLSchema-instance"><con:properties><con:property><con:name>_ticket</con:name><con:value>d332a25f5deaa5f998a90201c4bf84a1efd21c4ed57ae96c568597f9c64b48ad</con:value></con:property></con:properties></con:config></con:testStep><con:testStep type="restrequest" name="login" id="4ef50951-dd8b-4562-a9e2-b34bedf72a55"><con:settings/><con:config service="https://158.181.53.211" resourcePath="/login.json" methodName="Login.json" xsi:type="con:RestRequestStep" xmlns:xsi="http://www.w3.org/2001/XMLSchema-instance"><con:restRequest name="login" id="e1142e61-fb61-44c0-b83b-603616f7e725" mediaType="application/json" postQueryString="false"><con:settings><con:setting id="com.eviware.soapui.impl.wsdl.WsdlRequest@request-headers">&lt;xml-fragment/></con:setting></con:settings><con:endpoint>https://158.181.53.211</con:endpoint><con:request>{"username":"${TestData#username}","password":"${TestData#password}"}</con:request><con:originalUri>https://158.181.53.211/login.json</con:originalUri><con:assertion type="Valid HTTP Status Codes" id="6dccd3a2-4948-4941-a81a-c73f4c9ad712" name="Valid HTTP Status Codes"><con:configuration><codes>200</codes></con:configuration></con:assertion><con:assertion type="JsonPath Count" id="012c5635-5d9d-4099-aa08-b3a52e5dd8d9" name="JsonPath Count"><con:configuration><path>loginStatus.ticket</path><content>1</content><allowWildcards>false</allowWildcards><ignoreNamspaceDifferences>false</ignoreNamspaceDifferences><ignoreComments>false</ignoreComments></con:configuration></con:assertion><con:assertion type="JsonPath Match" id="cbbe1300-6cd9-48fe-8187-6d8f7313e030" name="JsonPath Match"><con:configuration><path>loginStatus.error</path><content>success</content><allowWildcards>false</allowWildcards><ignoreNamspaceDifferences>false</ignoreNamspaceDifferences><ignoreComments>false</ignoreComments></con:configuration></con:assertion><con:credentials><con:authType>No Authorization</con:authType></con:credentials><con:jmsConfig JMSDeliveryMode="PERSISTENT"/><con:jmsPropertyConfig/><con:parameters/></con:restRequest></con:config></con:testStep><con:testStep type="transfer" name="Property Transfer" id="b4afccc2-e7df-461d-b0b9-dcb4ad029f79"><con:settings/><con:config xsi:type="con:PropertyTransfersStep" xmlns:xsi="http://www.w3.org/2001/XMLSchema-instance"><con:transfers setNullOnMissingSource="true" transferTextContent="true" failOnError="true" ignoreEmpty="false" transferToAll="false" entitize="false" transferChildNodes="false"><con:name>ticket</con:name><con:sourceType>Response</con:sourceType><con:sourceStep>login</con:sourceStep><con:sourcePath>loginStatus.ticket</con:sourcePath><con:targetType>_ticket</con:targetType><con:targetStep>TEMP</con:targetStep><con:type>JSONPATH</con:type><con:targetTransferType>JSONPATH</con:targetTransferType><con:upgraded>true</con:upgraded></con:transfers></con:config></con:testStep><con:testStep type="restrequest" name="GetTableList" id="9a3af580-b693-445e-9728-38b5c70da946"><con:settings/><con:config service="https://mydev.ginstr.com" resourcePath="/api/ag/db/table" methodName="GETtables" xsi:type="con:RestRequestStep" xmlns:xsi="http://www.w3.org/2001/XMLSchema-instance"><con:restRequest name="GetTableList" id="edf50cf2-425c-428f-b79c-76fd038568d9" mediaType="application/json"><con:settings><con:setting id="com.eviware.soapui.impl.wsdl.WsdlRequest@request-headers">&lt;xml-fragment/></con:setting></con:settings><con:endpoint>https://mydev.ginstr.com</con:endpoint><con:request/><con:originalUri>https://mydev.ginstr.com/api/ag/db/table</con:originalUri><con:assertion type="Valid HTTP Status Codes" id="9e18d1d5-39b6-4158-a6dc-95950f68ef52" name="Valid HTTP Status Codes"><con:configuration><codes>200
</codes></con:configuration></con:assertion><con:credentials><con:authType>No Authorization</con:authType></con:credentials><con:jmsConfig JMSDeliveryMode="PERSISTENT"/><con:jmsPropertyConfig/><con:parameters><entry key="Authorization" value="${TEMP#_ticket}" xmlns="http://eviware.com/soapui/config"/></con:parameters></con:restRequest></con:config></con:testStep><con:testStep type="groovy" name="FindTheTable" id="71744822-1b1c-459e-81f7-c99640775fd2"><con:settings/><con:config><script>import groovy.json.JsonSlurper

tempTables = testRunner.testCase.getTestStepByName("GetTableList").getPropertyValue("response")
tableName = testRunner.testCase.getTestStepByName("TestData").getPropertyValue("tableName")
parsedTables = new JsonSlurper().parseText(tempTables)

parsedTables.each () {
  if (it.name == tableName) {
  	testRunner.testCase.getTestStepByName("DeleteTable").setPropertyValue("tableid",it._id)
  	testRunner.testCase.getTestStepByName("DeleteTable").run(testRunner, context)
   }
}</script></con:config></con:testStep><con:testStep type="restrequest" name="DeleteTable" id="7881d827-64c6-47a5-bdd3-2e10d343b598" disabled="true"><con:settings/><con:config service="https://mydev.ginstr.com" methodName="Method 1" resourcePath="/api/ag/db/table/{tableid}" xsi:type="con:RestRequestStep" xmlns:xsi="http://www.w3.org/2001/XMLSchema-instance"><con:restRequest name="DeleteTable" id="7cc8b4fe-5850-4689-bc81-446be4cea5de" mediaType="application/json" postQueryString="false"><con:settings><con:setting id="com.eviware.soapui.impl.wsdl.WsdlRequest@request-headers">&lt;xml-fragment/></con:setting></con:settings><con:encoding>UTF-8</con:encoding><con:endpoint>https://mydev.ginstr.com</con:endpoint><con:request/><con:originalUri>https://mydev.ginstr.com/api/ag/db/table</con:originalUri><con:credentials><con:authType>No Authorization</con:authType></con:credentials><con:jmsConfig JMSDeliveryMode="PERSISTENT"/><con:jmsPropertyConfig/><con:parameters>
  <con:entry key="tableid" value="mainUser111151__0231420e2f52491eb73ad22216752e17"/>
  <con:entry key="Authorization" value="${TEMP#_ticket}"/>
</con:parameters></con:restRequest></con:config></con:testStep><con:testStep type="restrequest" name="Create Table" id="9d9b26e4-85cc-4a6d-bc74-47988d21faed"><con:settings/><con:config service="https://mydev.ginstr.com" resourcePath="/api/ag/db/table" methodName="Table" xsi:type="con:RestRequestStep" xmlns:xsi="http://www.w3.org/2001/XMLSchema-instance"><con:restRequest name="Create Table" id="1ed9098e-1b3f-4f66-8a7c-f9962e43116c" mediaType="application/json" postQueryString="false"><con:settings><con:setting id="com.eviware.soapui.impl.wsdl.WsdlRequest@request-headers">&lt;xml-fragment/></con:setting></con:settings><con:endpoint>https://mydev.ginstr.com</con:endpoint><con:request>{"columns":[{"dataTypeDefinitionId":"text","id":"2eefe4c6f0bd406787d21fbb88a1a2f8","settings":{"len":null,"horizontalAlignment":"left","valuesList":[]},"name":"iti"}],"name":"${TestData#tableName}","isTableEmpty":true}</con:request><con:originalUri>https://mydev.ginstr.com/api/ag/db/table</con:originalUri><con:assertion type="Valid HTTP Status Codes" id="2120935b-1726-4870-bac3-d61d8b6a5f00" name="Valid HTTP Status Codes"><con:configuration><codes>200
</codes></con:configuration></con:assertion><con:assertion type="JsonPath Match" id="15b2d5af-67ec-4800-b8d6-575b91bb06d9" name="JsonPath Match"><con:configuration><path>name</path><content>${TestData#tableName}</content><allowWildcards>false</allowWildcards><ignoreNamspaceDifferences>false</ignoreNamspaceDifferences><ignoreComments>false</ignoreComments></con:configuration></con:assertion><con:credentials><con:authType>No Authorization</con:authType></con:credentials><con:jmsConfig JMSDeliveryMode="PERSISTENT"/><con:jmsPropertyConfig/><con:parameters>
  <con:entry key="Authorization" value="${TEMP#_ticket}"/>
  <con:entry key="tableid" value=""/>
  <con:entry key="autorization" value="1f092f9f11f76bd0370b01ba33cd98a00b04ba44abd9ad0cac5056aa89a5234b"/>
</con:parameters><con:parameterOrder><con:entry>Authorization</con:entry></con:parameterOrder></con:restRequest></con:config></con:testStep><con:properties/></con:testCase><con:properties/></con:testSuite><con:properties/><con:wssContainer/><con:oAuth2ProfileContainer/><con:sensitiveInformation/></con:soapui-project>